bhanuproject/__init__.py
bhanuproject/ann.py
bhanuproject/data.py
bhanuproject-1.0.dev20190307.dist-info/METADATA
bhanuproject-1.0.dev20190307.dist-info/WHEEL
bhanuproject-1.0.dev20190307.dist-info/top_level.txt
bhanuproject-1.0.dev20190307.dist-info/RECORD
